{
    "summary": {
        "success": 30,
        "failed": 0,
        "skipped": 0,
        "error": false,
        "disconnected": false,
        "exitCode": 0,
        "score": 100,
        "basicSupport": {
            "total": 16,
            "failed": 0,
            "passed": 16
        },
        "advancedSupport": {
            "total": 14,
            "failed": 0,
            "passed": 14
        }
    },
    "browsers": [
        {
            "browser": {
                "id": "48052372",
                "fullName": "FirefoxHeadless",
                "name": "FirefoxHeadless",
                "state": "DISCONNECTED",
                "lastResult": {
                    "startTime": 1641831170312,
                    "total": 15,
                    "success": 15,
                    "failed": 0,
                    "skipped": 0,
                    "totalTime": 240,
                    "netTime": 147,
                    "error": false,
                    "disconnected": false
                },
                "disconnectsCount": 0,
                "noActivityTimeout": 30000,
                "disconnectDelay": 2000
            },
            "errors": [],
            "results": [
                {
                    "id": "",
                    "description": "can display a Custom Element with no children",
                    "suite": [
                        "basic support",
                        "no children"
                    ],
                    "success": true,
                    "skipped": false,
                    "time": 8,
                    "log": [],
                    "assertionErrors": [],
                    "startTime": 1641831170310,
                    "endTime": 1641831170319,
                    "weight": 3
                },
                {
                    "id": "",
                    "description": "can display a Custom Element with children in a Shadow Root",
                    "suite": [
                        "basic support",
                        "with children"
                    ],
                    "success": true,
                    "skipped": false,
                    "time": 2,
                    "log": [],
                    "assertionErrors": [],
                    "startTime": 1641831170321,
                    "endTime": 1641831170323,
                    "weight": 3
                },
                {
                    "id": "",
                    "description": "can display a Custom Element with children in a Shadow Root and pass in Light DOM children",
                    "suite": [
                        "basic support",
                        "with children"
                    ],
                    "success": true,
                    "skipped": false,
                    "time": 29,
                    "log": [],
                    "assertionErrors": [],
                    "startTime": 1641831170324,
                    "endTime": 1641831170354,
                    "weight": 3
                },
                {
                    "id": "",
                    "description": "can display a Custom Element with children in the Shadow DOM and handle hiding and showing the element",
                    "suite": [
                        "basic support",
                        "with children"
                    ],
                    "success": true,
                    "skipped": false,
                    "time": 19,
                    "log": [],
                    "assertionErrors": [],
                    "startTime": 1641831170356,
                    "endTime": 1641831170376,
                    "weight": 3
                },
                {
                    "id": "",
                    "description": "will pass boolean data as either an attribute or a property",
                    "suite": [
                        "basic support",
                        "attributes and properties"
                    ],
                    "success": true,
                    "skipped": false,
                    "time": 14,
                    "log": [],
                    "assertionErrors": [],
                    "startTime": 1641831170386,
                    "endTime": 1641831170402,
                    "weight": 3
                },
                {
                    "id": "",
                    "description": "will pass numeric data as either an attribute or a property",
                    "suite": [
                        "basic support",
                        "attributes and properties"
                    ],
                    "success": true,
                    "skipped": false,
                    "time": 1,
                    "log": [],
                    "assertionErrors": [],
                    "startTime": 1641831170407,
                    "endTime": 1641831170408,
                    "weight": 3
                },
                {
                    "id": "",
                    "description": "will pass string data as either an attribute or a property",
                    "suite": [
                        "basic support",
                        "attributes and properties"
                    ],
                    "success": true,
                    "skipped": false,
                    "time": 1,
                    "log": [],
                    "assertionErrors": [],
                    "startTime": 1641831170408,
                    "endTime": 1641831170409,
                    "weight": 3
                },
                {
                    "id": "",
                    "description": "can imperatively listen to a DOM event dispatched by a Custom Element",
                    "suite": [
                        "basic support",
                        "events"
                    ],
                    "success": true,
                    "skipped": false,
                    "time": 12,
                    "log": [],
                    "assertionErrors": [],
                    "startTime": 1641831170411,
                    "endTime": 1641831170425,
                    "weight": 3
                },
                {
                    "id": "",
                    "description": "will pass array data as a property",
                    "suite": [
                        "advanced support",
                        "attributes and properties"
                    ],
                    "success": true,
                    "skipped": false,
                    "time": 2,
                    "log": [],
                    "assertionErrors": [],
                    "startTime": 1641831170434,
                    "endTime": 1641831170436,
                    "weight": 2
                },
                {
                    "id": "",
                    "description": "will pass object data as a property",
                    "suite": [
                        "advanced support",
                        "attributes and properties"
                    ],
                    "success": true,
                    "skipped": false,
                    "time": 2,
                    "log": [],
                    "assertionErrors": [],
                    "startTime": 1641831170441,
                    "endTime": 1641831170443,
                    "weight": 2
                },
                {
                    "id": "",
                    "description": "can declaratively listen to a lowercase DOM event dispatched by a Custom Element",
                    "suite": [
                        "advanced support",
                        "events"
                    ],
                    "success": true,
                    "skipped": false,
                    "time": 12,
                    "log": [],
                    "assertionErrors": [],
                    "startTime": 1641831170447,
                    "endTime": 1641831170459,
                    "weight": 2
                },
                {
                    "id": "",
                    "description": "can declaratively listen to a kebab-case DOM event dispatched by a Custom Element",
                    "suite": [
                        "advanced support",
                        "events"
                    ],
                    "success": true,
                    "skipped": false,
                    "time": 12,
                    "log": [],
                    "assertionErrors": [],
                    "startTime": 1641831170464,
                    "endTime": 1641831170478,
                    "weight": 1
                },
                {
                    "id": "",
                    "description": "can declaratively listen to a camelCase DOM event dispatched by a Custom Element",
                    "suite": [
                        "advanced support",
                        "events"
                    ],
                    "success": true,
                    "skipped": false,
                    "time": 11,
                    "log": [],
                    "assertionErrors": [],
                    "startTime": 1641831170484,
                    "endTime": 1641831170495,
                    "weight": 1
                },
                {
                    "id": "",
                    "description": "can declaratively listen to a CAPScase DOM event dispatched by a Custom Element",
                    "suite": [
                        "advanced support",
                        "events"
                    ],
                    "success": true,
                    "skipped": false,
                    "time": 12,
                    "log": [],
                    "assertionErrors": [],
                    "startTime": 1641831170500,
                    "endTime": 1641831170512,
                    "weight": 1
                },
                {
                    "id": "",
                    "description": "can declaratively listen to a PascalCase DOM event dispatched by a Custom Element",
                    "suite": [
                        "advanced support",
                        "events"
                    ],
                    "success": true,
                    "skipped": false,
                    "time": 10,
                    "log": [],
                    "assertionErrors": [],
                    "startTime": 1641831170517,
                    "endTime": 1641831170528,
                    "weight": 1
                }
            ]
        },
        {
            "browser": {
                "id": "63813287",
                "fullName": "Mozilla/5.0 (X11; Linux x86_64) AppleWebKit/537.36 (KHTML, like Gecko) HeadlessChrome/96.0.4664.110 Safari/537.36",
                "name": "Chrome Headless 96.0.4664.110 (Linux x86_64)",
                "state": "DISCONNECTED",
                "lastResult": {
                    "startTime": 1641831167881,
                    "total": 15,
                    "success": 15,
                    "failed": 0,
                    "skipped": 0,
                    "totalTime": 191,
                    "netTime": 121,
                    "error": false,
                    "disconnected": false
                },
                "disconnectsCount": 0,
                "noActivityTimeout": 30000,
                "disconnectDelay": 2000
            },
            "errors": [],
            "results": [
                {
                    "id": "",
                    "description": "can display a Custom Element with no children",
                    "suite": [
                        "basic support",
                        "no children"
                    ],
                    "success": true,
                    "skipped": false,
                    "time": 2,
                    "log": [],
                    "assertionErrors": [],
                    "startTime": 1641831167893,
                    "endTime": 1641831167896,
                    "weight": 3
                },
                {
                    "id": "",
                    "description": "can display a Custom Element with children in a Shadow Root",
                    "suite": [
                        "basic support",
                        "with children"
                    ],
                    "success": true,
                    "skipped": false,
                    "time": 1,
                    "log": [],
                    "assertionErrors": [],
                    "startTime": 1641831167896,
                    "endTime": 1641831167897,
                    "weight": 3
                },
                {
                    "id": "",
                    "description": "can display a Custom Element with children in a Shadow Root and pass in Light DOM children",
                    "suite": [
                        "basic support",
                        "with children"
                    ],
                    "success": true,
                    "skipped": false,
                    "time": 30,
                    "log": [],
                    "assertionErrors": [],
                    "startTime": 1641831167898,
                    "endTime": 1641831167929,
                    "weight": 3
                },
                {
                    "id": "",
                    "description": "can display a Custom Element with children in the Shadow DOM and handle hiding and showing the element",
                    "suite": [
                        "basic support",
                        "with children"
                    ],
                    "success": true,
                    "skipped": false,
                    "time": 14,
                    "log": [],
                    "assertionErrors": [],
                    "startTime": 1641831167931,
                    "endTime": 1641831167946,
                    "weight": 3
                },
                {
                    "id": "",
                    "description": "will pass boolean data as either an attribute or a property",
                    "suite": [
                        "basic support",
                        "attributes and properties"
                    ],
                    "success": true,
                    "skipped": false,
                    "time": 2,
                    "log": [],
                    "assertionErrors": [],
                    "startTime": 1641831167953,
                    "endTime": 1641831167956,
                    "weight": 3
                },
                {
                    "id": "",
                    "description": "will pass numeric data as either an attribute or a property",
                    "suite": [
                        "basic support",
                        "attributes and properties"
                    ],
                    "success": true,
                    "skipped": false,
                    "time": 1,
                    "log": [],
                    "assertionErrors": [],
                    "startTime": 1641831167957,
                    "endTime": 1641831167958,
                    "weight": 3
                },
                {
                    "id": "",
                    "description": "will pass string data as either an attribute or a property",
                    "suite": [
                        "basic support",
                        "attributes and properties"
                    ],
                    "success": true,
                    "skipped": false,
                    "time": 2,
                    "log": [],
                    "assertionErrors": [],
                    "startTime": 1641831167958,
                    "endTime": 1641831167960,
                    "weight": 3
                },
                {
                    "id": "",
                    "description": "can imperatively listen to a DOM event dispatched by a Custom Element",
                    "suite": [
                        "basic support",
                        "events"
                    ],
                    "success": true,
                    "skipped": false,
                    "time": 12,
                    "log": [],
                    "assertionErrors": [],
                    "startTime": 1641831167961,
                    "endTime": 1641831167973,
                    "weight": 3
                },
                {
                    "id": "",
                    "description": "will pass array data as a property",
                    "suite": [
                        "advanced support",
                        "attributes and properties"
                    ],
                    "success": true,
                    "skipped": false,
                    "time": 1,
                    "log": [],
                    "assertionErrors": [],
                    "startTime": 1641831167977,
                    "endTime": 1641831167978,
                    "weight": 2
                },
                {
                    "id": "",
                    "description": "will pass object data as a property",
                    "suite": [
                        "advanced support",
                        "attributes and properties"
                    ],
                    "success": true,
                    "skipped": false,
                    "time": 1,
                    "log": [],
                    "assertionErrors": [],
                    "startTime": 1641831167983,
                    "endTime": 1641831167984,
                    "weight": 2
                },
                {
                    "id": "",
                    "description": "can declaratively listen to a lowercase DOM event dispatched by a Custom Element",
                    "suite": [
                        "advanced support",
                        "events"
                    ],
                    "success": true,
                    "skipped": false,
                    "time": 11,
                    "log": [],
                    "assertionErrors": [],
                    "startTime": 1641831167988,
                    "endTime": 1641831168000,
                    "weight": 2
                },
                {
                    "id": "",
                    "description": "can declaratively listen to a kebab-case DOM event dispatched by a Custom Element",
                    "suite": [
                        "advanced support",
                        "events"
                    ],
                    "success": true,
                    "skipped": false,
                    "time": 11,
                    "log": [],
                    "assertionErrors": [],
                    "startTime": 1641831168006,
                    "endTime": 1641831168017,
                    "weight": 1
                },
                {
                    "id": "",
                    "description": "can declaratively listen to a camelCase DOM event dispatched by a Custom Element",
                    "suite": [
                        "advanced support",
                        "events"
                    ],
                    "success": true,
                    "skipped": false,
                    "time": 11,
                    "log": [],
                    "assertionErrors": [],
                    "startTime": 1641831168022,
                    "endTime": 1641831168033,
                    "weight": 1
                },
                {
                    "id": "",
                    "description": "can declaratively listen to a CAPScase DOM event dispatched by a Custom Element",
                    "suite": [
                        "advanced support",
                        "events"
                    ],
                    "success": true,
                    "skipped": false,
                    "time": 11,
                    "log": [],
                    "assertionErrors": [],
                    "startTime": 1641831168038,
                    "endTime": 1641831168049,
                    "weight": 1
                },
                {
                    "id": "",
                    "description": "can declaratively listen to a PascalCase DOM event dispatched by a Custom Element",
                    "suite": [
                        "advanced support",
                        "events"
                    ],
                    "success": true,
                    "skipped": false,
                    "time": 11,
                    "log": [],
                    "assertionErrors": [],
                    "startTime": 1641831168055,
                    "endTime": 1641831168066,
                    "weight": 1
                }
            ]
        }
    ],
    "library": {
        "name": "hyperhtml",
        "version": "2.34.0"
    }
}