{
    "summary": {
        "success": 32,
        "failed": 0,
        "skipped": 0,
        "error": false,
        "disconnected": false,
        "exitCode": 0,
        "score": 100,
        "basicSupport": {
            "total": 16,
            "failed": 0,
            "passed": 16
        },
        "advancedSupport": {
            "total": 16,
            "failed": 0,
            "passed": 16
        }
    },
    "browsers": [
        {
            "browser": {
                "id": "45687235",
                "fullName": "Mozilla/5.0 (X11; Linux x86_64) AppleWebKit/537.36 (KHTML, like Gecko) HeadlessChrome/138.0.0.0 Safari/537.36",
                "name": "Chrome Headless 138.0.0.0 (Linux x86_64)",
                "state": "DISCONNECTED",
                "lastResult": {
                    "startTime": 1754845291910,
                    "total": 16,
                    "success": 16,
                    "failed": 0,
                    "skipped": 0,
                    "totalTime": 465,
                    "netTime": 302,
                    "error": false,
                    "disconnected": false
                },
                "disconnectsCount": 0,
                "noActivityTimeout": 30000,
                "disconnectDelay": 2000
            },
            "errors": [],
            "results": [
                {
                    "id": "",
                    "description": "can display a Custom Element with no children",
                    "suite": [
                        "basic support",
                        "no children"
                    ],
                    "success": true,
                    "skipped": false,
                    "time": 131,
                    "log": [],
                    "assertionErrors": [],
                    "startTime": 1754845291899,
                    "endTime": 1754845292032,
                    "weight": 3
                },
                {
                    "id": "",
                    "description": "can display a Custom Element with children in a Shadow Root",
                    "suite": [
                        "basic support",
                        "with children"
                    ],
                    "success": true,
                    "skipped": false,
                    "time": 10,
                    "log": [],
                    "assertionErrors": [],
                    "startTime": 1754845292057,
                    "endTime": 1754845292074,
                    "weight": 3
                },
                {
                    "id": "",
                    "description": "can display a Custom Element with children in a Shadow Root and pass in Light DOM children",
                    "suite": [
                        "basic support",
                        "with children"
                    ],
                    "success": true,
                    "skipped": false,
                    "time": 39,
                    "log": [],
                    "assertionErrors": [],
                    "startTime": 1754845292074,
                    "endTime": 1754845292113,
                    "weight": 3
                },
                {
                    "id": "",
                    "description": "can display a Custom Element with children in the Shadow DOM and handle hiding and showing the element",
                    "suite": [
                        "basic support",
                        "with children"
                    ],
                    "success": true,
                    "skipped": false,
                    "time": 37,
                    "log": [],
                    "assertionErrors": [],
                    "startTime": 1754845292146,
                    "endTime": 1754845292183,
                    "weight": 3
                },
                {
                    "id": "",
                    "description": "will pass boolean data as either an attribute or a property",
                    "suite": [
                        "basic support",
                        "attributes and properties"
                    ],
                    "success": true,
                    "skipped": false,
                    "time": 19,
                    "log": [],
                    "assertionErrors": [],
                    "startTime": 1754845292186,
                    "endTime": 1754845292205,
                    "weight": 3
                },
                {
                    "id": "",
                    "description": "will pass numeric data as either an attribute or a property",
                    "suite": [
                        "basic support",
                        "attributes and properties"
                    ],
                    "success": true,
                    "skipped": false,
                    "time": 2,
                    "log": [],
                    "assertionErrors": [],
                    "startTime": 1754845292205,
                    "endTime": 1754845292207,
                    "weight": 3
                },
                {
                    "id": "",
                    "description": "will pass string data as either an attribute or a property",
                    "suite": [
                        "basic support",
                        "attributes and properties"
                    ],
                    "success": true,
                    "skipped": false,
                    "time": 3,
                    "log": [],
                    "assertionErrors": [],
                    "startTime": 1754845292208,
                    "endTime": 1754845292211,
                    "weight": 3
                },
                {
                    "id": "",
                    "description": "can imperatively listen to a DOM event dispatched by a Custom Element",
                    "suite": [
                        "basic support",
                        "events"
                    ],
                    "success": true,
                    "skipped": false,
                    "time": 18,
                    "log": [],
                    "assertionErrors": [],
                    "startTime": 1754845292214,
                    "endTime": 1754845292232,
                    "weight": 3
                },
                {
                    "id": "",
                    "description": "will pass array data as a property",
                    "suite": [
                        "advanced support",
                        "attributes and properties"
                    ],
                    "success": true,
                    "skipped": false,
                    "time": 1,
                    "log": [],
                    "assertionErrors": [],
                    "startTime": 1754845292240,
                    "endTime": 1754845292241,
                    "weight": 2
                },
                {
                    "id": "",
                    "description": "will pass object data as a property",
                    "suite": [
                        "advanced support",
                        "attributes and properties"
                    ],
                    "success": true,
                    "skipped": false,
                    "time": 6,
                    "log": [],
                    "assertionErrors": [],
                    "startTime": 1754845292249,
                    "endTime": 1754845292255,
                    "weight": 2
                },
                {
                    "id": "",
                    "description": "will pass object data to a camelCase-named property",
                    "suite": [
                        "advanced support",
                        "attributes and properties"
                    ],
                    "success": true,
                    "skipped": false,
                    "time": 1,
                    "log": [],
                    "assertionErrors": [],
                    "startTime": 1754845292255,
                    "endTime": 1754845292256,
                    "weight": 2
                },
                {
                    "id": "",
                    "description": "can declaratively listen to a lowercase DOM event dispatched by a Custom Element",
                    "suite": [
                        "advanced support",
                        "events"
                    ],
                    "success": true,
                    "skipped": false,
                    "time": 18,
                    "log": [],
                    "assertionErrors": [],
                    "startTime": 1754845292256,
                    "endTime": 1754845292283,
                    "weight": 2
                },
                {
                    "id": "",
                    "description": "can declaratively listen to a kebab-case DOM event dispatched by a Custom Element",
                    "suite": [
                        "advanced support",
                        "events"
                    ],
                    "success": true,
                    "skipped": false,
                    "time": 10,
                    "log": [],
                    "assertionErrors": [],
                    "startTime": 1754845292296,
                    "endTime": 1754845292306,
                    "weight": 1
                },
                {
                    "id": "",
                    "description": "can declaratively listen to a camelCase DOM event dispatched by a Custom Element",
                    "suite": [
                        "advanced support",
                        "events"
                    ],
                    "success": true,
                    "skipped": false,
                    "time": 1,
                    "log": [],
                    "assertionErrors": [],
                    "startTime": 1754845292320,
                    "endTime": 1754845292321,
                    "weight": 1
                },
                {
                    "id": "",
                    "description": "can declaratively listen to a CAPScase DOM event dispatched by a Custom Element",
                    "suite": [
                        "advanced support",
                        "events"
                    ],
                    "success": true,
                    "skipped": false,
                    "time": 1,
                    "log": [],
                    "assertionErrors": [],
                    "startTime": 1754845292341,
                    "endTime": 1754845292342,
                    "weight": 1
                },
                {
                    "id": "",
                    "description": "can declaratively listen to a PascalCase DOM event dispatched by a Custom Element",
                    "suite": [
                        "advanced support",
                        "events"
                    ],
                    "success": true,
                    "skipped": false,
                    "time": 5,
                    "log": [],
                    "assertionErrors": [],
                    "startTime": 1754845292353,
                    "endTime": 1754845292358,
                    "weight": 1
                }
            ]
        },
        {
            "browser": {
                "id": "93562735",
                "fullName": "FirefoxHeadless",
                "name": "FirefoxHeadless",
                "state": "DISCONNECTED",
                "lastResult": {
                    "startTime": 1754845305207,
                    "total": 16,
                    "success": 16,
                    "failed": 0,
                    "skipped": 0,
                    "totalTime": 339,
                    "netTime": 214,
                    "error": false,
                    "disconnected": false
                },
                "disconnectsCount": 0,
                "noActivityTimeout": 30000,
                "disconnectDelay": 2000
            },
            "errors": [],
            "results": [
                {
                    "id": "",
                    "description": "can display a Custom Element with no children",
                    "suite": [
                        "basic support",
                        "no children"
                    ],
                    "success": true,
                    "skipped": false,
                    "time": 59,
                    "log": [],
                    "assertionErrors": [],
                    "startTime": 1754845305195,
                    "endTime": 1754845305256,
                    "weight": 3
                },
                {
                    "id": "",
                    "description": "can display a Custom Element with children in a Shadow Root",
                    "suite": [
                        "basic support",
                        "with children"
                    ],
                    "success": true,
                    "skipped": false,
                    "time": 7,
                    "log": [],
                    "assertionErrors": [],
                    "startTime": 1754845305257,
                    "endTime": 1754845305264,
                    "weight": 3
                },
                {
                    "id": "",
                    "description": "can display a Custom Element with children in a Shadow Root and pass in Light DOM children",
                    "suite": [
                        "basic support",
                        "with children"
                    ],
                    "success": true,
                    "skipped": false,
                    "time": 34,
                    "log": [],
                    "assertionErrors": [],
                    "startTime": 1754845305264,
                    "endTime": 1754845305298,
                    "weight": 3
                },
                {
                    "id": "",
                    "description": "can display a Custom Element with children in the Shadow DOM and handle hiding and showing the element",
                    "suite": [
                        "basic support",
                        "with children"
                    ],
                    "success": true,
                    "skipped": false,
                    "time": 25,
                    "log": [],
                    "assertionErrors": [],
                    "startTime": 1754845305308,
                    "endTime": 1754845305333,
                    "weight": 3
                },
                {
                    "id": "",
                    "description": "will pass boolean data as either an attribute or a property",
                    "suite": [
                        "basic support",
                        "attributes and properties"
                    ],
                    "success": true,
                    "skipped": false,
                    "time": 11,
                    "log": [],
                    "assertionErrors": [],
                    "startTime": 1754845305336,
                    "endTime": 1754845305351,
                    "weight": 3
                },
                {
                    "id": "",
                    "description": "will pass numeric data as either an attribute or a property",
                    "suite": [
                        "basic support",
                        "attributes and properties"
                    ],
                    "success": true,
                    "skipped": false,
                    "time": 1,
                    "log": [],
                    "assertionErrors": [],
                    "startTime": 1754845305354,
                    "endTime": 1754845305355,
                    "weight": 3
                },
                {
                    "id": "",
                    "description": "will pass string data as either an attribute or a property",
                    "suite": [
                        "basic support",
                        "attributes and properties"
                    ],
                    "success": true,
                    "skipped": false,
                    "time": 5,
                    "log": [],
                    "assertionErrors": [],
                    "startTime": 1754845305356,
                    "endTime": 1754845305361,
                    "weight": 3
                },
                {
                    "id": "",
                    "description": "can imperatively listen to a DOM event dispatched by a Custom Element",
                    "suite": [
                        "basic support",
                        "events"
                    ],
                    "success": true,
                    "skipped": false,
                    "time": 7,
                    "log": [],
                    "assertionErrors": [],
                    "startTime": 1754845305362,
                    "endTime": 1754845305369,
                    "weight": 3
                },
                {
                    "id": "",
                    "description": "will pass array data as a property",
                    "suite": [
                        "advanced support",
                        "attributes and properties"
                    ],
                    "success": true,
                    "skipped": false,
                    "time": 3,
                    "log": [],
                    "assertionErrors": [],
                    "startTime": 1754845305377,
                    "endTime": 1754845305380,
                    "weight": 2
                },
                {
                    "id": "",
                    "description": "will pass object data as a property",
                    "suite": [
                        "advanced support",
                        "attributes and properties"
                    ],
                    "success": true,
                    "skipped": false,
                    "time": 2,
                    "log": [],
                    "assertionErrors": [],
                    "startTime": 1754845305382,
                    "endTime": 1754845305384,
                    "weight": 2
                },
                {
                    "id": "",
                    "description": "will pass object data to a camelCase-named property",
                    "suite": [
                        "advanced support",
                        "attributes and properties"
                    ],
                    "success": true,
                    "skipped": false,
                    "time": 7,
                    "log": [],
                    "assertionErrors": [],
                    "startTime": 1754845305384,
                    "endTime": 1754845305391,
                    "weight": 2
                },
                {
                    "id": "",
                    "description": "can declaratively listen to a lowercase DOM event dispatched by a Custom Element",
                    "suite": [
                        "advanced support",
                        "events"
                    ],
                    "success": true,
                    "skipped": false,
                    "time": 26,
                    "log": [],
                    "assertionErrors": [],
                    "startTime": 1754845305391,
                    "endTime": 1754845305418,
                    "weight": 2
                },
                {
                    "id": "",
                    "description": "can declaratively listen to a kebab-case DOM event dispatched by a Custom Element",
                    "suite": [
                        "advanced support",
                        "events"
                    ],
                    "success": true,
                    "skipped": false,
                    "time": 6,
                    "log": [],
                    "assertionErrors": [],
                    "startTime": 1754845305422,
                    "endTime": 1754845305429,
                    "weight": 1
                },
                {
                    "id": "",
                    "description": "can declaratively listen to a camelCase DOM event dispatched by a Custom Element",
                    "suite": [
                        "advanced support",
                        "events"
                    ],
                    "success": true,
                    "skipped": false,
                    "time": 8,
                    "log": [],
                    "assertionErrors": [],
                    "startTime": 1754845305438,
                    "endTime": 1754845305446,
                    "weight": 1
                },
                {
                    "id": "",
                    "description": "can declaratively listen to a CAPScase DOM event dispatched by a Custom Element",
                    "suite": [
                        "advanced support",
                        "events"
                    ],
                    "success": true,
                    "skipped": false,
                    "time": 8,
                    "log": [],
                    "assertionErrors": [],
                    "startTime": 1754845305458,
                    "endTime": 1754845305466,
                    "weight": 1
                },
                {
                    "id": "",
                    "description": "can declaratively listen to a PascalCase DOM event dispatched by a Custom Element",
                    "suite": [
                        "advanced support",
                        "events"
                    ],
                    "success": true,
                    "skipped": false,
                    "time": 5,
                    "log": [],
                    "assertionErrors": [],
                    "startTime": 1754845305476,
                    "endTime": 1754845305481,
                    "weight": 1
                }
            ]
        }
    ],
    "library": {
        "name": "vue",
        "version": "^3.2.38"
    }
}