{
    "summary": {
        "success": 30,
        "failed": 0,
        "skipped": 0,
        "error": false,
        "disconnected": false,
        "exitCode": 0,
        "score": 100,
        "basicSupport": {
            "total": 16,
            "failed": 0,
            "passed": 16
        },
        "advancedSupport": {
            "total": 14,
            "failed": 0,
            "passed": 14
        }
    },
    "browsers": [
        {
            "browser": {
                "id": "81626757",
                "fullName": "Mozilla/5.0 (X11; Linux x86_64) AppleWebKit/537.36 (KHTML, like Gecko) HeadlessChrome/98.0.4758.80 Safari/537.36",
                "name": "Chrome Headless 98.0.4758.80 (Linux x86_64)",
                "state": "DISCONNECTED",
                "lastResult": {
                    "startTime": 1645139027278,
                    "total": 15,
                    "success": 15,
                    "failed": 0,
                    "skipped": 0,
                    "totalTime": 157,
                    "netTime": 119,
                    "error": false,
                    "disconnected": false
                },
                "disconnectsCount": 0,
                "noActivityTimeout": 30000,
                "disconnectDelay": 2000
            },
            "errors": [],
            "results": [
                {
                    "id": "",
                    "description": "can display a Custom Element with no children",
                    "suite": [
                        "basic support",
                        "no children"
                    ],
                    "success": true,
                    "skipped": false,
                    "time": 3,
                    "log": [],
                    "assertionErrors": [],
                    "startTime": 1645139027288,
                    "endTime": 1645139027291,
                    "weight": 3
                },
                {
                    "id": "",
                    "description": "can display a Custom Element with children in a Shadow Root",
                    "suite": [
                        "basic support",
                        "with children"
                    ],
                    "success": true,
                    "skipped": false,
                    "time": 1,
                    "log": [],
                    "assertionErrors": [],
                    "startTime": 1645139027292,
                    "endTime": 1645139027293,
                    "weight": 3
                },
                {
                    "id": "",
                    "description": "can display a Custom Element with children in a Shadow Root and pass in Light DOM children",
                    "suite": [
                        "basic support",
                        "with children"
                    ],
                    "success": true,
                    "skipped": false,
                    "time": 19,
                    "log": [],
                    "assertionErrors": [],
                    "startTime": 1645139027293,
                    "endTime": 1645139027312,
                    "weight": 3
                },
                {
                    "id": "",
                    "description": "can display a Custom Element with children in the Shadow DOM and handle hiding and showing the element",
                    "suite": [
                        "basic support",
                        "with children"
                    ],
                    "success": true,
                    "skipped": false,
                    "time": 17,
                    "log": [],
                    "assertionErrors": [],
                    "startTime": 1645139027315,
                    "endTime": 1645139027332,
                    "weight": 3
                },
                {
                    "id": "",
                    "description": "will pass boolean data as either an attribute or a property",
                    "suite": [
                        "basic support",
                        "attributes and properties"
                    ],
                    "success": true,
                    "skipped": false,
                    "time": 1,
                    "log": [],
                    "assertionErrors": [],
                    "startTime": 1645139027333,
                    "endTime": 1645139027334,
                    "weight": 3
                },
                {
                    "id": "",
                    "description": "will pass numeric data as either an attribute or a property",
                    "suite": [
                        "basic support",
                        "attributes and properties"
                    ],
                    "success": true,
                    "skipped": false,
                    "time": 0,
                    "log": [],
                    "assertionErrors": [],
                    "startTime": 1645139027334,
                    "endTime": 1645139027334,
                    "weight": 3
                },
                {
                    "id": "",
                    "description": "will pass string data as either an attribute or a property",
                    "suite": [
                        "basic support",
                        "attributes and properties"
                    ],
                    "success": true,
                    "skipped": false,
                    "time": 0,
                    "log": [],
                    "assertionErrors": [],
                    "startTime": 1645139027335,
                    "endTime": 1645139027335,
                    "weight": 3
                },
                {
                    "id": "",
                    "description": "can imperatively listen to a DOM event dispatched by a Custom Element",
                    "suite": [
                        "basic support",
                        "events"
                    ],
                    "success": true,
                    "skipped": false,
                    "time": 14,
                    "log": [],
                    "assertionErrors": [],
                    "startTime": 1645139027335,
                    "endTime": 1645139027349,
                    "weight": 3
                },
                {
                    "id": "",
                    "description": "will pass array data as a property",
                    "suite": [
                        "advanced support",
                        "attributes and properties"
                    ],
                    "success": true,
                    "skipped": false,
                    "time": 1,
                    "log": [],
                    "assertionErrors": [],
                    "startTime": 1645139027351,
                    "endTime": 1645139027352,
                    "weight": 2
                },
                {
                    "id": "",
                    "description": "will pass object data as a property",
                    "suite": [
                        "advanced support",
                        "attributes and properties"
                    ],
                    "success": true,
                    "skipped": false,
                    "time": 1,
                    "log": [],
                    "assertionErrors": [],
                    "startTime": 1645139027355,
                    "endTime": 1645139027356,
                    "weight": 2
                },
                {
                    "id": "",
                    "description": "can declaratively listen to a lowercase DOM event dispatched by a Custom Element",
                    "suite": [
                        "advanced support",
                        "events"
                    ],
                    "success": true,
                    "skipped": false,
                    "time": 7,
                    "log": [],
                    "assertionErrors": [],
                    "startTime": 1645139027359,
                    "endTime": 1645139027366,
                    "weight": 2
                },
                {
                    "id": "",
                    "description": "can declaratively listen to a kebab-case DOM event dispatched by a Custom Element",
                    "suite": [
                        "advanced support",
                        "events"
                    ],
                    "success": true,
                    "skipped": false,
                    "time": 13,
                    "log": [],
                    "assertionErrors": [],
                    "startTime": 1645139027369,
                    "endTime": 1645139027382,
                    "weight": 1
                },
                {
                    "id": "",
                    "description": "can declaratively listen to a camelCase DOM event dispatched by a Custom Element",
                    "suite": [
                        "advanced support",
                        "events"
                    ],
                    "success": true,
                    "skipped": false,
                    "time": 15,
                    "log": [],
                    "assertionErrors": [],
                    "startTime": 1645139027384,
                    "endTime": 1645139027399,
                    "weight": 1
                },
                {
                    "id": "",
                    "description": "can declaratively listen to a CAPScase DOM event dispatched by a Custom Element",
                    "suite": [
                        "advanced support",
                        "events"
                    ],
                    "success": true,
                    "skipped": false,
                    "time": 13,
                    "log": [],
                    "assertionErrors": [],
                    "startTime": 1645139027401,
                    "endTime": 1645139027415,
                    "weight": 1
                },
                {
                    "id": "",
                    "description": "can declaratively listen to a PascalCase DOM event dispatched by a Custom Element",
                    "suite": [
                        "advanced support",
                        "events"
                    ],
                    "success": true,
                    "skipped": false,
                    "time": 14,
                    "log": [],
                    "assertionErrors": [],
                    "startTime": 1645139027418,
                    "endTime": 1645139027432,
                    "weight": 1
                }
            ]
        },
        {
            "browser": {
                "id": "85843611",
                "fullName": "FirefoxHeadless",
                "name": "FirefoxHeadless",
                "state": "DISCONNECTED",
                "lastResult": {
                    "startTime": 1645139029368,
                    "total": 15,
                    "success": 15,
                    "failed": 0,
                    "skipped": 0,
                    "totalTime": 153,
                    "netTime": 116,
                    "error": false,
                    "disconnected": false
                },
                "disconnectsCount": 0,
                "noActivityTimeout": 30000,
                "disconnectDelay": 2000
            },
            "errors": [],
            "results": [
                {
                    "id": "",
                    "description": "can display a Custom Element with no children",
                    "suite": [
                        "basic support",
                        "no children"
                    ],
                    "success": true,
                    "skipped": false,
                    "time": 3,
                    "log": [],
                    "assertionErrors": [],
                    "startTime": 1645139029362,
                    "endTime": 1645139029365,
                    "weight": 3
                },
                {
                    "id": "",
                    "description": "can display a Custom Element with children in a Shadow Root",
                    "suite": [
                        "basic support",
                        "with children"
                    ],
                    "success": true,
                    "skipped": false,
                    "time": 0,
                    "log": [],
                    "assertionErrors": [],
                    "startTime": 1645139029367,
                    "endTime": 1645139029369,
                    "weight": 3
                },
                {
                    "id": "",
                    "description": "can display a Custom Element with children in a Shadow Root and pass in Light DOM children",
                    "suite": [
                        "basic support",
                        "with children"
                    ],
                    "success": true,
                    "skipped": false,
                    "time": 6,
                    "log": [],
                    "assertionErrors": [],
                    "startTime": 1645139029369,
                    "endTime": 1645139029376,
                    "weight": 3
                },
                {
                    "id": "",
                    "description": "can display a Custom Element with children in the Shadow DOM and handle hiding and showing the element",
                    "suite": [
                        "basic support",
                        "with children"
                    ],
                    "success": true,
                    "skipped": false,
                    "time": 31,
                    "log": [],
                    "assertionErrors": [],
                    "startTime": 1645139029380,
                    "endTime": 1645139029411,
                    "weight": 3
                },
                {
                    "id": "",
                    "description": "will pass boolean data as either an attribute or a property",
                    "suite": [
                        "basic support",
                        "attributes and properties"
                    ],
                    "success": true,
                    "skipped": false,
                    "time": 1,
                    "log": [],
                    "assertionErrors": [],
                    "startTime": 1645139029415,
                    "endTime": 1645139029420,
                    "weight": 3
                },
                {
                    "id": "",
                    "description": "will pass numeric data as either an attribute or a property",
                    "suite": [
                        "basic support",
                        "attributes and properties"
                    ],
                    "success": true,
                    "skipped": false,
                    "time": 0,
                    "log": [],
                    "assertionErrors": [],
                    "startTime": 1645139029420,
                    "endTime": 1645139029421,
                    "weight": 3
                },
                {
                    "id": "",
                    "description": "will pass string data as either an attribute or a property",
                    "suite": [
                        "basic support",
                        "attributes and properties"
                    ],
                    "success": true,
                    "skipped": false,
                    "time": 0,
                    "log": [],
                    "assertionErrors": [],
                    "startTime": 1645139029421,
                    "endTime": 1645139029422,
                    "weight": 3
                },
                {
                    "id": "",
                    "description": "can imperatively listen to a DOM event dispatched by a Custom Element",
                    "suite": [
                        "basic support",
                        "events"
                    ],
                    "success": true,
                    "skipped": false,
                    "time": 5,
                    "log": [],
                    "assertionErrors": [],
                    "startTime": 1645139029422,
                    "endTime": 1645139029427,
                    "weight": 3
                },
                {
                    "id": "",
                    "description": "will pass array data as a property",
                    "suite": [
                        "advanced support",
                        "attributes and properties"
                    ],
                    "success": true,
                    "skipped": false,
                    "time": 1,
                    "log": [],
                    "assertionErrors": [],
                    "startTime": 1645139029430,
                    "endTime": 1645139029432,
                    "weight": 2
                },
                {
                    "id": "",
                    "description": "will pass object data as a property",
                    "suite": [
                        "advanced support",
                        "attributes and properties"
                    ],
                    "success": true,
                    "skipped": false,
                    "time": 0,
                    "log": [],
                    "assertionErrors": [],
                    "startTime": 1645139029433,
                    "endTime": 1645139029433,
                    "weight": 2
                },
                {
                    "id": "",
                    "description": "can declaratively listen to a lowercase DOM event dispatched by a Custom Element",
                    "suite": [
                        "advanced support",
                        "events"
                    ],
                    "success": true,
                    "skipped": false,
                    "time": 8,
                    "log": [],
                    "assertionErrors": [],
                    "startTime": 1645139029434,
                    "endTime": 1645139029442,
                    "weight": 2
                },
                {
                    "id": "",
                    "description": "can declaratively listen to a kebab-case DOM event dispatched by a Custom Element",
                    "suite": [
                        "advanced support",
                        "events"
                    ],
                    "success": true,
                    "skipped": false,
                    "time": 14,
                    "log": [],
                    "assertionErrors": [],
                    "startTime": 1645139029444,
                    "endTime": 1645139029458,
                    "weight": 1
                },
                {
                    "id": "",
                    "description": "can declaratively listen to a camelCase DOM event dispatched by a Custom Element",
                    "suite": [
                        "advanced support",
                        "events"
                    ],
                    "success": true,
                    "skipped": false,
                    "time": 16,
                    "log": [],
                    "assertionErrors": [],
                    "startTime": 1645139029460,
                    "endTime": 1645139029476,
                    "weight": 1
                },
                {
                    "id": "",
                    "description": "can declaratively listen to a CAPScase DOM event dispatched by a Custom Element",
                    "suite": [
                        "advanced support",
                        "events"
                    ],
                    "success": true,
                    "skipped": false,
                    "time": 16,
                    "log": [],
                    "assertionErrors": [],
                    "startTime": 1645139029477,
                    "endTime": 1645139029493,
                    "weight": 1
                },
                {
                    "id": "",
                    "description": "can declaratively listen to a PascalCase DOM event dispatched by a Custom Element",
                    "suite": [
                        "advanced support",
                        "events"
                    ],
                    "success": true,
                    "skipped": false,
                    "time": 15,
                    "log": [],
                    "assertionErrors": [],
                    "startTime": 1645139029495,
                    "endTime": 1645139029511,
                    "weight": 1
                }
            ]
        }
    ],
    "library": {
        "name": "mithril",
        "version": "2.0.4"
    }
}