{
    "summary": {
        "success": 30,
        "failed": 0,
        "skipped": 0,
        "error": false,
        "disconnected": false,
        "exitCode": 0,
        "score": 100,
        "basicSupport": {
            "total": 16,
            "failed": 0,
            "passed": 16
        },
        "advancedSupport": {
            "total": 14,
            "failed": 0,
            "passed": 14
        }
    },
    "browsers": [
        {
            "browser": {
                "id": "50098632",
                "fullName": "Mozilla/5.0 (X11; Linux x86_64) AppleWebKit/537.36 (KHTML, like Gecko) HeadlessChrome/97.0.4692.71 Safari/537.36",
                "name": "Chrome Headless 97.0.4692.71 (Linux x86_64)",
                "state": "DISCONNECTED",
                "lastResult": {
                    "startTime": 1642418648676,
                    "total": 15,
                    "success": 15,
                    "failed": 0,
                    "skipped": 0,
                    "totalTime": 295,
                    "netTime": 250,
                    "error": false,
                    "disconnected": false
                },
                "disconnectsCount": 0,
                "noActivityTimeout": 30000,
                "disconnectDelay": 2000
            },
            "errors": [],
            "results": [
                {
                    "id": "",
                    "description": "can display a Custom Element with no children",
                    "suite": [
                        "basic support",
                        "no children"
                    ],
                    "success": true,
                    "skipped": false,
                    "time": 6,
                    "log": [],
                    "assertionErrors": [],
                    "startTime": 1642418648680,
                    "endTime": 1642418648687,
                    "weight": 3
                },
                {
                    "id": "",
                    "description": "can display a Custom Element with children in a Shadow Root",
                    "suite": [
                        "basic support",
                        "with children"
                    ],
                    "success": true,
                    "skipped": false,
                    "time": 10,
                    "log": [],
                    "assertionErrors": [],
                    "startTime": 1642418648690,
                    "endTime": 1642418648701,
                    "weight": 3
                },
                {
                    "id": "",
                    "description": "can display a Custom Element with children in a Shadow Root and pass in Light DOM children",
                    "suite": [
                        "basic support",
                        "with children"
                    ],
                    "success": true,
                    "skipped": false,
                    "time": 28,
                    "log": [],
                    "assertionErrors": [],
                    "startTime": 1642418648705,
                    "endTime": 1642418648733,
                    "weight": 3
                },
                {
                    "id": "",
                    "description": "can display a Custom Element with children in the Shadow DOM and handle hiding and showing the element",
                    "suite": [
                        "basic support",
                        "with children"
                    ],
                    "success": true,
                    "skipped": false,
                    "time": 48,
                    "log": [],
                    "assertionErrors": [],
                    "startTime": 1642418648735,
                    "endTime": 1642418648784,
                    "weight": 3
                },
                {
                    "id": "",
                    "description": "will pass boolean data as either an attribute or a property",
                    "suite": [
                        "basic support",
                        "attributes and properties"
                    ],
                    "success": true,
                    "skipped": false,
                    "time": 13,
                    "log": [],
                    "assertionErrors": [],
                    "startTime": 1642418648787,
                    "endTime": 1642418648801,
                    "weight": 3
                },
                {
                    "id": "",
                    "description": "will pass numeric data as either an attribute or a property",
                    "suite": [
                        "basic support",
                        "attributes and properties"
                    ],
                    "success": true,
                    "skipped": false,
                    "time": 14,
                    "log": [],
                    "assertionErrors": [],
                    "startTime": 1642418648803,
                    "endTime": 1642418648817,
                    "weight": 3
                },
                {
                    "id": "",
                    "description": "will pass string data as either an attribute or a property",
                    "suite": [
                        "basic support",
                        "attributes and properties"
                    ],
                    "success": true,
                    "skipped": false,
                    "time": 15,
                    "log": [],
                    "assertionErrors": [],
                    "startTime": 1642418648819,
                    "endTime": 1642418648834,
                    "weight": 3
                },
                {
                    "id": "",
                    "description": "can imperatively listen to a DOM event dispatched by a Custom Element",
                    "suite": [
                        "basic support",
                        "events"
                    ],
                    "success": true,
                    "skipped": false,
                    "time": 15,
                    "log": [],
                    "assertionErrors": [],
                    "startTime": 1642418648836,
                    "endTime": 1642418648851,
                    "weight": 3
                },
                {
                    "id": "",
                    "description": "will pass array data as a property",
                    "suite": [
                        "advanced support",
                        "attributes and properties"
                    ],
                    "success": true,
                    "skipped": false,
                    "time": 12,
                    "log": [],
                    "assertionErrors": [],
                    "startTime": 1642418648854,
                    "endTime": 1642418648867,
                    "weight": 2
                },
                {
                    "id": "",
                    "description": "will pass object data as a property",
                    "suite": [
                        "advanced support",
                        "attributes and properties"
                    ],
                    "success": true,
                    "skipped": false,
                    "time": 14,
                    "log": [],
                    "assertionErrors": [],
                    "startTime": 1642418648870,
                    "endTime": 1642418648884,
                    "weight": 2
                },
                {
                    "id": "",
                    "description": "can declaratively listen to a lowercase DOM event dispatched by a Custom Element",
                    "suite": [
                        "advanced support",
                        "events"
                    ],
                    "success": true,
                    "skipped": false,
                    "time": 13,
                    "log": [],
                    "assertionErrors": [],
                    "startTime": 1642418648886,
                    "endTime": 1642418648900,
                    "weight": 2
                },
                {
                    "id": "",
                    "description": "can declaratively listen to a kebab-case DOM event dispatched by a Custom Element",
                    "suite": [
                        "advanced support",
                        "events"
                    ],
                    "success": true,
                    "skipped": false,
                    "time": 15,
                    "log": [],
                    "assertionErrors": [],
                    "startTime": 1642418648902,
                    "endTime": 1642418648917,
                    "weight": 1
                },
                {
                    "id": "",
                    "description": "can declaratively listen to a camelCase DOM event dispatched by a Custom Element",
                    "suite": [
                        "advanced support",
                        "events"
                    ],
                    "success": true,
                    "skipped": false,
                    "time": 16,
                    "log": [],
                    "assertionErrors": [],
                    "startTime": 1642418648918,
                    "endTime": 1642418648934,
                    "weight": 1
                },
                {
                    "id": "",
                    "description": "can declaratively listen to a CAPScase DOM event dispatched by a Custom Element",
                    "suite": [
                        "advanced support",
                        "events"
                    ],
                    "success": true,
                    "skipped": false,
                    "time": 14,
                    "log": [],
                    "assertionErrors": [],
                    "startTime": 1642418648936,
                    "endTime": 1642418648950,
                    "weight": 1
                },
                {
                    "id": "",
                    "description": "can declaratively listen to a PascalCase DOM event dispatched by a Custom Element",
                    "suite": [
                        "advanced support",
                        "events"
                    ],
                    "success": true,
                    "skipped": false,
                    "time": 17,
                    "log": [],
                    "assertionErrors": [],
                    "startTime": 1642418648952,
                    "endTime": 1642418648969,
                    "weight": 1
                }
            ]
        },
        {
            "browser": {
                "id": "53347383",
                "fullName": "FirefoxHeadless",
                "name": "FirefoxHeadless",
                "state": "DISCONNECTED",
                "lastResult": {
                    "startTime": 1642418651929,
                    "total": 15,
                    "success": 15,
                    "failed": 0,
                    "skipped": 0,
                    "totalTime": 297,
                    "netTime": 242,
                    "error": false,
                    "disconnected": false
                },
                "disconnectsCount": 0,
                "noActivityTimeout": 30000,
                "disconnectDelay": 2000
            },
            "errors": [],
            "results": [
                {
                    "id": "",
                    "description": "can display a Custom Element with no children",
                    "suite": [
                        "basic support",
                        "no children"
                    ],
                    "success": true,
                    "skipped": false,
                    "time": 10,
                    "log": [],
                    "assertionErrors": [],
                    "startTime": 1642418651934,
                    "endTime": 1642418651944,
                    "weight": 3
                },
                {
                    "id": "",
                    "description": "can display a Custom Element with children in a Shadow Root",
                    "suite": [
                        "basic support",
                        "with children"
                    ],
                    "success": true,
                    "skipped": false,
                    "time": 3,
                    "log": [],
                    "assertionErrors": [],
                    "startTime": 1642418651952,
                    "endTime": 1642418651955,
                    "weight": 3
                },
                {
                    "id": "",
                    "description": "can display a Custom Element with children in a Shadow Root and pass in Light DOM children",
                    "suite": [
                        "basic support",
                        "with children"
                    ],
                    "success": true,
                    "skipped": false,
                    "time": 19,
                    "log": [],
                    "assertionErrors": [],
                    "startTime": 1642418651967,
                    "endTime": 1642418651987,
                    "weight": 3
                },
                {
                    "id": "",
                    "description": "can display a Custom Element with children in the Shadow DOM and handle hiding and showing the element",
                    "suite": [
                        "basic support",
                        "with children"
                    ],
                    "success": true,
                    "skipped": false,
                    "time": 46,
                    "log": [],
                    "assertionErrors": [],
                    "startTime": 1642418651991,
                    "endTime": 1642418652039,
                    "weight": 3
                },
                {
                    "id": "",
                    "description": "will pass boolean data as either an attribute or a property",
                    "suite": [
                        "basic support",
                        "attributes and properties"
                    ],
                    "success": true,
                    "skipped": false,
                    "time": 15,
                    "log": [],
                    "assertionErrors": [],
                    "startTime": 1642418652040,
                    "endTime": 1642418652056,
                    "weight": 3
                },
                {
                    "id": "",
                    "description": "will pass numeric data as either an attribute or a property",
                    "suite": [
                        "basic support",
                        "attributes and properties"
                    ],
                    "success": true,
                    "skipped": false,
                    "time": 14,
                    "log": [],
                    "assertionErrors": [],
                    "startTime": 1642418652057,
                    "endTime": 1642418652072,
                    "weight": 3
                },
                {
                    "id": "",
                    "description": "will pass string data as either an attribute or a property",
                    "suite": [
                        "basic support",
                        "attributes and properties"
                    ],
                    "success": true,
                    "skipped": false,
                    "time": 15,
                    "log": [],
                    "assertionErrors": [],
                    "startTime": 1642418652073,
                    "endTime": 1642418652088,
                    "weight": 3
                },
                {
                    "id": "",
                    "description": "can imperatively listen to a DOM event dispatched by a Custom Element",
                    "suite": [
                        "basic support",
                        "events"
                    ],
                    "success": true,
                    "skipped": false,
                    "time": 16,
                    "log": [],
                    "assertionErrors": [],
                    "startTime": 1642418652090,
                    "endTime": 1642418652107,
                    "weight": 3
                },
                {
                    "id": "",
                    "description": "will pass array data as a property",
                    "suite": [
                        "advanced support",
                        "attributes and properties"
                    ],
                    "success": true,
                    "skipped": false,
                    "time": 15,
                    "log": [],
                    "assertionErrors": [],
                    "startTime": 1642418652108,
                    "endTime": 1642418652124,
                    "weight": 2
                },
                {
                    "id": "",
                    "description": "will pass object data as a property",
                    "suite": [
                        "advanced support",
                        "attributes and properties"
                    ],
                    "success": true,
                    "skipped": false,
                    "time": 14,
                    "log": [],
                    "assertionErrors": [],
                    "startTime": 1642418652125,
                    "endTime": 1642418652139,
                    "weight": 2
                },
                {
                    "id": "",
                    "description": "can declaratively listen to a lowercase DOM event dispatched by a Custom Element",
                    "suite": [
                        "advanced support",
                        "events"
                    ],
                    "success": true,
                    "skipped": false,
                    "time": 16,
                    "log": [],
                    "assertionErrors": [],
                    "startTime": 1642418652140,
                    "endTime": 1642418652156,
                    "weight": 2
                },
                {
                    "id": "",
                    "description": "can declaratively listen to a kebab-case DOM event dispatched by a Custom Element",
                    "suite": [
                        "advanced support",
                        "events"
                    ],
                    "success": true,
                    "skipped": false,
                    "time": 13,
                    "log": [],
                    "assertionErrors": [],
                    "startTime": 1642418652157,
                    "endTime": 1642418652171,
                    "weight": 1
                },
                {
                    "id": "",
                    "description": "can declaratively listen to a camelCase DOM event dispatched by a Custom Element",
                    "suite": [
                        "advanced support",
                        "events"
                    ],
                    "success": true,
                    "skipped": false,
                    "time": 15,
                    "log": [],
                    "assertionErrors": [],
                    "startTime": 1642418652173,
                    "endTime": 1642418652188,
                    "weight": 1
                },
                {
                    "id": "",
                    "description": "can declaratively listen to a CAPScase DOM event dispatched by a Custom Element",
                    "suite": [
                        "advanced support",
                        "events"
                    ],
                    "success": true,
                    "skipped": false,
                    "time": 15,
                    "log": [],
                    "assertionErrors": [],
                    "startTime": 1642418652189,
                    "endTime": 1642418652204,
                    "weight": 1
                },
                {
                    "id": "",
                    "description": "can declaratively listen to a PascalCase DOM event dispatched by a Custom Element",
                    "suite": [
                        "advanced support",
                        "events"
                    ],
                    "success": true,
                    "skipped": false,
                    "time": 16,
                    "log": [],
                    "assertionErrors": [],
                    "startTime": 1642418652204,
                    "endTime": 1642418652221,
                    "weight": 1
                }
            ]
        }
    ],
    "library": {
        "name": "hybrids",
        "version": "4.3.4"
    }
}