{
    "summary": {
        "success": 32,
        "failed": 0,
        "skipped": 0,
        "error": false,
        "disconnected": false,
        "exitCode": 0,
        "score": 100,
        "basicSupport": {
            "total": 16,
            "failed": 0,
            "passed": 16
        },
        "advancedSupport": {
            "total": 16,
            "failed": 0,
            "passed": 16
        }
    },
    "browsers": [
        {
            "browser": {
                "id": "11464820",
                "fullName": "Mozilla/5.0 (X11; Linux x86_64) AppleWebKit/537.36 (KHTML, like Gecko) HeadlessChrome/138.0.0.0 Safari/537.36",
                "name": "Chrome Headless 138.0.0.0 (Linux x86_64)",
                "state": "DISCONNECTED",
                "lastResult": {
                    "startTime": 1754688286480,
                    "total": 16,
                    "success": 16,
                    "failed": 0,
                    "skipped": 0,
                    "totalTime": 241,
                    "netTime": 113,
                    "error": false,
                    "disconnected": false
                },
                "disconnectsCount": 0,
                "noActivityTimeout": 30000,
                "disconnectDelay": 2000
            },
            "errors": [],
            "results": [
                {
                    "id": "",
                    "description": "can display a Custom Element with no children",
                    "suite": [
                        "basic support",
                        "no children"
                    ],
                    "success": true,
                    "skipped": false,
                    "time": 22,
                    "log": [],
                    "assertionErrors": [],
                    "startTime": 1754688286483,
                    "endTime": 1754688286507,
                    "weight": 3
                },
                {
                    "id": "",
                    "description": "can display a Custom Element with children in a Shadow Root",
                    "suite": [
                        "basic support",
                        "with children"
                    ],
                    "success": true,
                    "skipped": false,
                    "time": 1,
                    "log": [],
                    "assertionErrors": [],
                    "startTime": 1754688286508,
                    "endTime": 1754688286515,
                    "weight": 3
                },
                {
                    "id": "",
                    "description": "can display a Custom Element with children in a Shadow Root and pass in Light DOM children",
                    "suite": [
                        "basic support",
                        "with children"
                    ],
                    "success": true,
                    "skipped": false,
                    "time": 17,
                    "log": [],
                    "assertionErrors": [],
                    "startTime": 1754688286515,
                    "endTime": 1754688286532,
                    "weight": 3
                },
                {
                    "id": "",
                    "description": "can display a Custom Element with children in the Shadow DOM and handle hiding and showing the element",
                    "suite": [
                        "basic support",
                        "with children"
                    ],
                    "success": true,
                    "skipped": false,
                    "time": 2,
                    "log": [],
                    "assertionErrors": [],
                    "startTime": 1754688286532,
                    "endTime": 1754688286534,
                    "weight": 3
                },
                {
                    "id": "",
                    "description": "will pass boolean data as either an attribute or a property",
                    "suite": [
                        "basic support",
                        "attributes and properties"
                    ],
                    "success": true,
                    "skipped": false,
                    "time": 15,
                    "log": [],
                    "assertionErrors": [],
                    "startTime": 1754688286534,
                    "endTime": 1754688286549,
                    "weight": 3
                },
                {
                    "id": "",
                    "description": "will pass numeric data as either an attribute or a property",
                    "suite": [
                        "basic support",
                        "attributes and properties"
                    ],
                    "success": true,
                    "skipped": false,
                    "time": 4,
                    "log": [],
                    "assertionErrors": [],
                    "startTime": 1754688286549,
                    "endTime": 1754688286553,
                    "weight": 3
                },
                {
                    "id": "",
                    "description": "will pass string data as either an attribute or a property",
                    "suite": [
                        "basic support",
                        "attributes and properties"
                    ],
                    "success": true,
                    "skipped": false,
                    "time": 0,
                    "log": [],
                    "assertionErrors": [],
                    "startTime": 1754688286553,
                    "endTime": 1754688286554,
                    "weight": 3
                },
                {
                    "id": "",
                    "description": "can imperatively listen to a DOM event dispatched by a Custom Element",
                    "suite": [
                        "basic support",
                        "events"
                    ],
                    "success": true,
                    "skipped": false,
                    "time": 15,
                    "log": [],
                    "assertionErrors": [],
                    "startTime": 1754688286554,
                    "endTime": 1754688286569,
                    "weight": 3
                },
                {
                    "id": "",
                    "description": "will pass array data as a property",
                    "suite": [
                        "advanced support",
                        "attributes and properties"
                    ],
                    "success": true,
                    "skipped": false,
                    "time": 1,
                    "log": [],
                    "assertionErrors": [],
                    "startTime": 1754688286569,
                    "endTime": 1754688286570,
                    "weight": 2
                },
                {
                    "id": "",
                    "description": "will pass object data as a property",
                    "suite": [
                        "advanced support",
                        "attributes and properties"
                    ],
                    "success": true,
                    "skipped": false,
                    "time": 20,
                    "log": [],
                    "assertionErrors": [],
                    "startTime": 1754688286570,
                    "endTime": 1754688286590,
                    "weight": 2
                },
                {
                    "id": "",
                    "description": "will pass object data to a camelCase-named property",
                    "suite": [
                        "advanced support",
                        "attributes and properties"
                    ],
                    "success": true,
                    "skipped": false,
                    "time": 5,
                    "log": [],
                    "assertionErrors": [],
                    "startTime": 1754688286601,
                    "endTime": 1754688286606,
                    "weight": 2
                },
                {
                    "id": "",
                    "description": "can declaratively listen to a lowercase DOM event dispatched by a Custom Element",
                    "suite": [
                        "advanced support",
                        "events"
                    ],
                    "success": true,
                    "skipped": false,
                    "time": 11,
                    "log": [],
                    "assertionErrors": [],
                    "startTime": 1754688286606,
                    "endTime": 1754688286617,
                    "weight": 2
                },
                {
                    "id": "",
                    "description": "can declaratively listen to a kebab-case DOM event dispatched by a Custom Element",
                    "suite": [
                        "advanced support",
                        "events"
                    ],
                    "success": true,
                    "skipped": false,
                    "time": 0,
                    "log": [],
                    "assertionErrors": [],
                    "startTime": 1754688286617,
                    "endTime": 1754688286617,
                    "weight": 1
                },
                {
                    "id": "",
                    "description": "can declaratively listen to a camelCase DOM event dispatched by a Custom Element",
                    "suite": [
                        "advanced support",
                        "events"
                    ],
                    "success": true,
                    "skipped": false,
                    "time": 0,
                    "log": [],
                    "assertionErrors": [],
                    "startTime": 1754688286618,
                    "endTime": 1754688286618,
                    "weight": 1
                },
                {
                    "id": "",
                    "description": "can declaratively listen to a CAPScase DOM event dispatched by a Custom Element",
                    "suite": [
                        "advanced support",
                        "events"
                    ],
                    "success": true,
                    "skipped": false,
                    "time": 0,
                    "log": [],
                    "assertionErrors": [],
                    "startTime": 1754688286623,
                    "endTime": 1754688286623,
                    "weight": 1
                },
                {
                    "id": "",
                    "description": "can declaratively listen to a PascalCase DOM event dispatched by a Custom Element",
                    "suite": [
                        "advanced support",
                        "events"
                    ],
                    "success": true,
                    "skipped": false,
                    "time": 0,
                    "log": [],
                    "assertionErrors": [],
                    "startTime": 1754688286624,
                    "endTime": 1754688286624,
                    "weight": 1
                }
            ]
        },
        {
            "browser": {
                "id": "88537728",
                "fullName": "FirefoxHeadless",
                "name": "FirefoxHeadless",
                "state": "DISCONNECTED",
                "lastResult": {
                    "startTime": 1754688296114,
                    "total": 16,
                    "success": 16,
                    "failed": 0,
                    "skipped": 0,
                    "totalTime": 10,
                    "netTime": 76,
                    "error": false,
                    "disconnected": false
                },
                "disconnectsCount": 0,
                "noActivityTimeout": 30000,
                "disconnectDelay": 2000
            },
            "errors": [],
            "results": [
                {
                    "id": "",
                    "description": "can display a Custom Element with no children",
                    "suite": [
                        "basic support",
                        "no children"
                    ],
                    "success": true,
                    "skipped": false,
                    "time": 25,
                    "log": [],
                    "assertionErrors": [],
                    "startTime": 1754688295839,
                    "endTime": 1754688295868,
                    "weight": 3
                },
                {
                    "id": "",
                    "description": "can display a Custom Element with children in a Shadow Root",
                    "suite": [
                        "basic support",
                        "with children"
                    ],
                    "success": true,
                    "skipped": false,
                    "time": 13,
                    "log": [],
                    "assertionErrors": [],
                    "startTime": 1754688295869,
                    "endTime": 1754688295882,
                    "weight": 3
                },
                {
                    "id": "",
                    "description": "can display a Custom Element with children in a Shadow Root and pass in Light DOM children",
                    "suite": [
                        "basic support",
                        "with children"
                    ],
                    "success": true,
                    "skipped": false,
                    "time": 2,
                    "log": [],
                    "assertionErrors": [],
                    "startTime": 1754688295883,
                    "endTime": 1754688295898,
                    "weight": 3
                },
                {
                    "id": "",
                    "description": "can display a Custom Element with children in the Shadow DOM and handle hiding and showing the element",
                    "suite": [
                        "basic support",
                        "with children"
                    ],
                    "success": true,
                    "skipped": false,
                    "time": 9,
                    "log": [],
                    "assertionErrors": [],
                    "startTime": 1754688295898,
                    "endTime": 1754688295907,
                    "weight": 3
                },
                {
                    "id": "",
                    "description": "will pass boolean data as either an attribute or a property",
                    "suite": [
                        "basic support",
                        "attributes and properties"
                    ],
                    "success": true,
                    "skipped": false,
                    "time": 1,
                    "log": [],
                    "assertionErrors": [],
                    "startTime": 1754688295908,
                    "endTime": 1754688295909,
                    "weight": 3
                },
                {
                    "id": "",
                    "description": "will pass numeric data as either an attribute or a property",
                    "suite": [
                        "basic support",
                        "attributes and properties"
                    ],
                    "success": true,
                    "skipped": false,
                    "time": 7,
                    "log": [],
                    "assertionErrors": [],
                    "startTime": 1754688295909,
                    "endTime": 1754688295916,
                    "weight": 3
                },
                {
                    "id": "",
                    "description": "will pass string data as either an attribute or a property",
                    "suite": [
                        "basic support",
                        "attributes and properties"
                    ],
                    "success": true,
                    "skipped": false,
                    "time": 0,
                    "log": [],
                    "assertionErrors": [],
                    "startTime": 1754688295916,
                    "endTime": 1754688295917,
                    "weight": 3
                },
                {
                    "id": "",
                    "description": "can imperatively listen to a DOM event dispatched by a Custom Element",
                    "suite": [
                        "basic support",
                        "events"
                    ],
                    "success": true,
                    "skipped": false,
                    "time": 3,
                    "log": [],
                    "assertionErrors": [],
                    "startTime": 1754688295918,
                    "endTime": 1754688295921,
                    "weight": 3
                },
                {
                    "id": "",
                    "description": "will pass array data as a property",
                    "suite": [
                        "advanced support",
                        "attributes and properties"
                    ],
                    "success": true,
                    "skipped": false,
                    "time": 2,
                    "log": [],
                    "assertionErrors": [],
                    "startTime": 1754688295922,
                    "endTime": 1754688295924,
                    "weight": 2
                },
                {
                    "id": "",
                    "description": "will pass object data as a property",
                    "suite": [
                        "advanced support",
                        "attributes and properties"
                    ],
                    "success": true,
                    "skipped": false,
                    "time": 1,
                    "log": [],
                    "assertionErrors": [],
                    "startTime": 1754688295928,
                    "endTime": 1754688295929,
                    "weight": 2
                },
                {
                    "id": "",
                    "description": "will pass object data to a camelCase-named property",
                    "suite": [
                        "advanced support",
                        "attributes and properties"
                    ],
                    "success": true,
                    "skipped": false,
                    "time": 1,
                    "log": [],
                    "assertionErrors": [],
                    "startTime": 1754688295929,
                    "endTime": 1754688295930,
                    "weight": 2
                },
                {
                    "id": "",
                    "description": "can declaratively listen to a lowercase DOM event dispatched by a Custom Element",
                    "suite": [
                        "advanced support",
                        "events"
                    ],
                    "success": true,
                    "skipped": false,
                    "time": 2,
                    "log": [],
                    "assertionErrors": [],
                    "startTime": 1754688295933,
                    "endTime": 1754688295935,
                    "weight": 2
                },
                {
                    "id": "",
                    "description": "can declaratively listen to a kebab-case DOM event dispatched by a Custom Element",
                    "suite": [
                        "advanced support",
                        "events"
                    ],
                    "success": true,
                    "skipped": false,
                    "time": 4,
                    "log": [],
                    "assertionErrors": [],
                    "startTime": 1754688295941,
                    "endTime": 1754688295945,
                    "weight": 1
                },
                {
                    "id": "",
                    "description": "can declaratively listen to a camelCase DOM event dispatched by a Custom Element",
                    "suite": [
                        "advanced support",
                        "events"
                    ],
                    "success": true,
                    "skipped": false,
                    "time": 1,
                    "log": [],
                    "assertionErrors": [],
                    "startTime": 1754688295945,
                    "endTime": 1754688295946,
                    "weight": 1
                },
                {
                    "id": "",
                    "description": "can declaratively listen to a CAPScase DOM event dispatched by a Custom Element",
                    "suite": [
                        "advanced support",
                        "events"
                    ],
                    "success": true,
                    "skipped": false,
                    "time": 1,
                    "log": [],
                    "assertionErrors": [],
                    "startTime": 1754688295946,
                    "endTime": 1754688295947,
                    "weight": 1
                },
                {
                    "id": "",
                    "description": "can declaratively listen to a PascalCase DOM event dispatched by a Custom Element",
                    "suite": [
                        "advanced support",
                        "events"
                    ],
                    "success": true,
                    "skipped": false,
                    "time": 4,
                    "log": [],
                    "assertionErrors": [],
                    "startTime": 1754688295947,
                    "endTime": 1754688295951,
                    "weight": 1
                }
            ]
        }
    ],
    "library": {
        "name": "riot",
        "version": "4.14.0"
    }
}